kbbi/__init__.py
kbbi/kbbi.py
kbbi-0.4.3.dist-info/LICENSE
kbbi-0.4.3.dist-info/METADATA
kbbi-0.4.3.dist-info/WHEEL
kbbi-0.4.3.dist-info/entry_points.txt
kbbi-0.4.3.dist-info/top_level.txt
kbbi-0.4.3.dist-info/RECORD
